chrome_pass/__init__.py
chrome_pass/__main__.py
chrome_pass-1.0.1.dist-info/METADATA
chrome_pass-1.0.1.dist-info/WHEEL
chrome_pass-1.0.1.dist-info/entry_points.txt
chrome_pass-1.0.1.dist-info/top_level.txt
chrome_pass-1.0.1.dist-info/RECORD
