Metadata-Version: 2.1
Name: chrome_pass
Version: 1.0.1
Summary: Native application for chrome-pass extension
Author-email: Horacio Sanson <hsanson@gmail.com>
License: MIT
Keywords: pass,chrome
Requires-Python: >=3.8
Requires-Dist: python-gnupg
Requires-Dist: pyotp
